octopus_sensing_visualizer/__init__.py
octopus_sensing_visualizer/end_point.py
octopus_sensing_visualizer/main.py
octopus_sensing_visualizer/prepare_data/__init__.py
octopus_sensing_visualizer/prepare_data/eeg.py
octopus_sensing_visualizer/prepare_data/gsr.py
octopus_sensing_visualizer/prepare_data/ppg.py
octopus_sensing_visualizer/ui_build/bundle.js
octopus_sensing_visualizer/ui_build/bundle.js.LICENSE.txt
octopus_sensing_visualizer/ui_build/chart.js
octopus_sensing_visualizer/ui_build/chart.js.map
octopus_sensing_visualizer/ui_build/dripicons-v2.woff
octopus_sensing_visualizer/ui_build/index.css
octopus_sensing_visualizer/ui_build/index.html
octopus_sensing_visualizer/ui_build/index.js
octopus_sensing_visualizer/ui_build/index.js.map
octopus_sensing_visualizer/ui_build/services.js
octopus_sensing_visualizer/ui_build/services.js.map
octopus_sensing_visualizer/ui_build/types.js
octopus_sensing_visualizer/ui_build/types.js.map
octopus_sensing_visualizer-1.3.0.dist-info/METADATA
octopus_sensing_visualizer-1.3.0.dist-info/WHEEL
octopus_sensing_visualizer-1.3.0.dist-info/entry_points.txt
octopus_sensing_visualizer-1.3.0.dist-info/RECORD
