Metadata-Version: 2.1
Name: octopus-sensing-visualizer
Version: 1.3.0
Summary: Library for visualizing data synchronously recorded from different sensors
Home-page: https://octopus-sensing.nastaran-saffar.me
License: GPL-3.0-or-later
Keywords: sensors,eeg,gsr,visualizer
Author: Nastaran Saffaryazdi
Author-email: nsaffar@gmail.com
Requires-Python: >=3.10,<4.0
Classifier: License :: OSI Approved :: GNU General Public License v3 or later (GPLv3+)
Classifier: Programming Language :: Python :: 3
Classifier: Programming Language :: Python :: 3.10
Classifier: Programming Language :: Python :: 3.11
Classifier: Programming Language :: Python :: 3.12
Requires-Dist: CherryPy (==18.10.0)
Requires-Dist: heartpy (==1.2.7)
Requires-Dist: neurokit2 (==0.2.10)
Requires-Dist: numpy (==2.2.2)
Requires-Dist: pandas (==2.2.3)
Requires-Dist: pycairo (==1.27.0)
Requires-Dist: requests (==2.32.3)
Project-URL: Repository, https://github.com/octopus-sensing/octopus-sensing-visualizer
